nkt_tools/NKTP_DLL.py
nkt_tools/__init__.py
nkt_tools/chatgpt_extend_uv.py
nkt_tools/chatgpt_select.py
nkt_tools/extreme.py
nkt_tools/varia.py
nkt_tools/NKTPDLL/__init__.py
nkt_tools/NKTPDLL/x64/NKTPDLL.dll
nkt_tools/NKTPDLL/x64/__init__.py
nkt_tools/NKTPDLL/x86/NKTPDLL.dll
nkt_tools/NKTPDLL/x86/__init__.py
nkt_tools-0.0.8.dist-info/LICENSE
nkt_tools-0.0.8.dist-info/METADATA
nkt_tools-0.0.8.dist-info/WHEEL
nkt_tools-0.0.8.dist-info/top_level.txt
nkt_tools-0.0.8.dist-info/RECORD
