Metadata-Version: 2.1
Name: nkt-tools
Version: 0.0.8
Summary: Python package for accessing NKT photonics project through NKTPDLL
Author-email: Briley Bourgeois <bbourge6@stanford.edu>
Project-URL: Homepage, https://github.com/Dionne-Lab/nkt_tools
Project-URL: Bug Tracker, https://github.com/Dionne-Lab/nkt_tools/issues
Classifier: Programming Language :: Python :: 3
Classifier: License :: OSI Approved :: MIT License
Classifier: Operating System :: OS Independent
Requires-Python: >=3.7
License-File: LICENSE
